en_motorinc_nlp/__init__.py
en_motorinc_nlp/custom_spacy_normalizer.py
en_motorinc_nlp/meta.json
en_motorinc_nlp/en_motorinc_nlp-0.0.3/README.md
en_motorinc_nlp/en_motorinc_nlp-0.0.3/config.cfg
en_motorinc_nlp/en_motorinc_nlp-0.0.3/meta.json
en_motorinc_nlp/en_motorinc_nlp-0.0.3/pattern_mapping.json
en_motorinc_nlp/en_motorinc_nlp-0.0.3/tokenizer
en_motorinc_nlp/en_motorinc_nlp-0.0.3/attribute_ruler/patterns
en_motorinc_nlp/en_motorinc_nlp-0.0.3/entity_ruler/cfg
en_motorinc_nlp/en_motorinc_nlp-0.0.3/entity_ruler/patterns.jsonl
en_motorinc_nlp/en_motorinc_nlp-0.0.3/lemmatizer/lookups/lookups.bin
en_motorinc_nlp/en_motorinc_nlp-0.0.3/ner/cfg
en_motorinc_nlp/en_motorinc_nlp-0.0.3/ner/model
en_motorinc_nlp/en_motorinc_nlp-0.0.3/ner/moves
en_motorinc_nlp/en_motorinc_nlp-0.0.3/parser/cfg
en_motorinc_nlp/en_motorinc_nlp-0.0.3/parser/model
en_motorinc_nlp/en_motorinc_nlp-0.0.3/parser/moves
en_motorinc_nlp/en_motorinc_nlp-0.0.3/senter/cfg
en_motorinc_nlp/en_motorinc_nlp-0.0.3/senter/model
en_motorinc_nlp/en_motorinc_nlp-0.0.3/tagger/cfg
en_motorinc_nlp/en_motorinc_nlp-0.0.3/tagger/model
en_motorinc_nlp/en_motorinc_nlp-0.0.3/tok2vec/cfg
en_motorinc_nlp/en_motorinc_nlp-0.0.3/tok2vec/model
en_motorinc_nlp/en_motorinc_nlp-0.0.3/vocab/key2row
en_motorinc_nlp/en_motorinc_nlp-0.0.3/vocab/lookups.bin
en_motorinc_nlp/en_motorinc_nlp-0.0.3/vocab/strings.json
en_motorinc_nlp/en_motorinc_nlp-0.0.3/vocab/vectors
en_motorinc_nlp/en_motorinc_nlp-0.0.3/vocab/vectors.cfg
en_motorinc_nlp-0.0.3.dist-info/METADATA
en_motorinc_nlp-0.0.3.dist-info/WHEEL
en_motorinc_nlp-0.0.3.dist-info/entry_points.txt
en_motorinc_nlp-0.0.3.dist-info/top_level.txt
en_motorinc_nlp-0.0.3.dist-info/RECORD
