Metadata-Version: 2.1
Name: en_motorinc_nlp
Version: 0.0.3
Summary: English pipeline optimized for CPU. Components: tok2vec, tagger, parser, senter, ner, attribute_ruler, lemmatizer.
Home-page: https://explosion.ai
Author: Explosion
Author-email: contact@explosion.ai
License: MIT
Requires-Dist: spacy<3.8.0,>=3.7.2
